<annotation>
	<folder>train</folder>
	<filename>triangle_181.jpg</filename>
	<path>/Users/maciejsaczewski/Documents/Inzynier/Object_detection_Coral/data/train/triangle_181.jpg</path>
	<source>
		<database>Unknown</database>
	</source>
	<size>
		<width>300</width>
		<height>300</height>
		<depth>3</depth>
	</size>
	<segmented>0</segmented>
	<object>
		<name>triangle</name>
		<pose>Unspecified</pose>
		<truncated>0</truncated>
		<difficult>0</difficult>
		<bndbox>
			<xmin>53</xmin>
			<ymin>209</ymin>
			<xmax>102</xmax>
			<ymax>255</ymax>
		</bndbox>
	</object>
</annotation>
